[
  {
    "href": "/game/7676",
    "text": "",
    "year": null
  },
  {
    "href": "/game/7676",
    "text": "Red Dead Redemption",
    "year": null
  },
  {
    "href": "/game/27100",
    "text": "",
    "year": null
  },
  {
    "href": "/game/27100",
    "text": "Red Dead Redemption 2",
    "year": null
  },
  {
    "href": "/game/39473",
    "text": "",
    "year": null
  },
  {
    "href": "/game/39473",
    "text": "Red Dead Redemption: Game of the Year Edition",
    "year": null
  },
  {
    "href": "/game/7677",
    "text": "",
    "year": null
  },
  {
    "href": "/game/7677",
    "text": "Red Dead Redemption: Undead Nightmare",
    "year": null
  },
  {
    "href": "/game/148211",
    "text": "",
    "year": null
  },
  {
    "href": "/game/148211",
    "text": "Deadrock Redemption",
    "year": null
  }
]